ecr_cli/__init__.py
ecr_cli/action.py
ecr_cli/cli.py
ecr_cli/client.py
ecr_cli/message.py
ecr_cli/model.py
ecr_cli/util.py
ecr_cli-0.0.8.dist-info/METADATA
ecr_cli-0.0.8.dist-info/RECORD
ecr_cli-0.0.8.dist-info/WHEEL
ecr_cli-0.0.8.dist-info/entry_points.txt
ecr_cli-0.0.8.dist-info/top_level.txt
