Metadata-Version: 2.1
Name: ecr-cli
Version: 0.0.8
Summary: Goodbye docker login & a long repository URL for Amazon ECR :)
Home-page: https://github.com/laughingman7743/ecr-cli/
Author: laughingman7743
Author-email: laughingman7743@gmail.com
License: MIT License
Platform: UNKNOWN
Classifier: Development Status :: 4 - Beta
Classifier: Intended Audience :: Developers
Classifier: License :: OSI Approved :: MIT License
Classifier: Operating System :: OS Independent
Classifier: Programming Language :: Python :: 2
Classifier: Programming Language :: Python :: 2.7
Classifier: Programming Language :: Python :: 3
Classifier: Programming Language :: Python :: 3.4
Classifier: Programming Language :: Python :: 3.5
Classifier: Programming Language :: Python :: 3.6
Requires-Dist: future
Requires-Dist: click (>=6.0)
Requires-Dist: PyYAML (>=3.12)
Requires-Dist: boto3 (>=1.5.0)
Requires-Dist: docker (>=3.1.0)
Requires-Dist: tqdm (>=4.19.0)
